requests/__init__.py
requests/__version__.py
requests/_internal_utils.py
requests/adapters.py
requests/api.py
requests/auth.py
requests/certs.py
requests/compat.py
requests/cookies.py
requests/exceptions.py
requests/help.py
requests/hooks.py
requests/models.py
requests/packages.py
requests/sessions.py
requests/status_codes.py
requests/structures.py
requests/utils.py
requests_ccwienk-2.21.1.dist-info/LICENSE
requests_ccwienk-2.21.1.dist-info/METADATA
requests_ccwienk-2.21.1.dist-info/WHEEL
requests_ccwienk-2.21.1.dist-info/top_level.txt
requests_ccwienk-2.21.1.dist-info/RECORD
